aawscd/__init__.py
aawscd/aawscd_copycat.py
aawscd/aawscd_getconf.py
aawscd/aawscd_pdcap.py
aawscd/aawscd_probmon.py
aawscd/aawscd_probwrite.py
aawscd/aawscd_setdirection.py
aawscd/aawscd_wwclient.py
aawscd/aawscd_wwrecord.py
aawscd/tools/__init__.py
aawscd/tools/prob.py
aawscd-1.0.1.dist-info/entry_points.txt
aawscd-1.0.1.dist-info/WHEEL
aawscd-1.0.1.dist-info/METADATA
aawscd-1.0.1.dist-info/RECORD
