Metadata-Version: 2.1
Name: aawscd
Version: 1.0.1
Summary: Utilities for the Aaware Sound Capture platform
Home-page: https://aaware.com
License: GPL-3.0-only
Author: Chris Eddington
Author-email: chris@aaware.com
Maintainer: Chris Eddington
Maintainer-email: chris@aaware.com
Requires-Python: >=3.8,<3.11
Classifier: License :: OSI Approved :: GNU General Public License v3 (GPLv3)
Classifier: Programming Language :: Python :: 3
Classifier: Programming Language :: Python :: 3.10
Classifier: Programming Language :: Python :: 3.8
Classifier: Programming Language :: Python :: 3.9
Requires-Dist: PyYAML (>=6.0,<7.0)
Requires-Dist: docopt (>=0.6,<0.7)
Requires-Dist: h5py (>=3,<4)
Requires-Dist: paho-mqtt (>=1.6.1,<2.0.0)
Requires-Dist: pyaaware (>=1.3.17,<2.0.0)
Requires-Dist: tqdm (>=4.62,<5.0)
